{
  "updated": "2026-04-18 03:28:00",
  "bot_config": {
    "active_strategy": "RSI_EMA",
    "rsi_buy": 35,
    "rsi_sell": 65,
    "stop_loss_pct": 2.0,
    "take_profit_pct": 4.0,
    "trade_usdt": 100.0,
    "candle_interval": "15m"
  },
  "balances": {
    "BTC": 0.99852,
    "USDT": 10305.4945992,
    "ETH": 0.9505,
    "SOL": 3.83
  },
  "positions": {
    "BTCUSDT": {
      "dca_count": 0,
      "entries": []
    },
    "ETHUSDT": {
      "dca_count": 0,
      "entries": []
    },
    "SOLUSDT": {
      "dca_count": 0,
      "entries": []
    }
  },
  "indicators": {
    "BTCUSDT": {
      "price": 77264.64,
      "rsi": 50.84,
      "ema200": 75919.8893,
      "rsi_buy_threshold": 35,
      "rsi_sell_threshold": 65,
      "rsi_to_buy": 15.84,
      "rsi_to_sell": 14.16,
      "price_above_ema200": true,
      "price_vs_ema200_pct": 1.77,
      "active_strategy": "RSI_EMA"
    },
    "ETHUSDT": {
      "price": 2416.8,
      "rsi": 44.31,
      "ema200": 2378.6003,
      "rsi_buy_threshold": 35,
      "rsi_sell_threshold": 65,
      "rsi_to_buy": 9.31,
      "rsi_to_sell": 20.69,
      "price_above_ema200": true,
      "price_vs_ema200_pct": 1.61,
      "active_strategy": "RSI_EMA"
    },
    "SOLUSDT": {
      "price": 88.84,
      "rsi": 44.86,
      "ema200": 87.8029,
      "rsi_buy_threshold": 35,
      "rsi_sell_threshold": 65,
      "rsi_to_buy": 9.86,
      "rsi_to_sell": 20.14,
      "price_above_ema200": true,
      "price_vs_ema200_pct": 1.18,
      "active_strategy": "RSI_EMA"
    }
  }
}