{
  "updated": "2026-04-16 05:16:58",
  "bot_config": {
    "active_strategy": "RSI_EMA",
    "rsi_buy": 35,
    "rsi_sell": 65,
    "stop_loss_pct": 2.0,
    "take_profit_pct": 4.0,
    "trade_usdt": 100.0,
    "candle_interval": "15m"
  },
  "balances": {
    "BTC": 0.99852,
    "USDT": 10305.4945992,
    "ETH": 0.9505,
    "SOL": 3.83
  },
  "positions": {
    "BTCUSDT": {
      "dca_count": 0,
      "entries": []
    },
    "ETHUSDT": {
      "dca_count": 0,
      "entries": []
    },
    "SOLUSDT": {
      "dca_count": 0,
      "entries": []
    }
  },
  "indicators": {
    "BTCUSDT": {
      "price": 74913.9,
      "rsi": 52.26,
      "ema200": 74228.8865,
      "rsi_buy_threshold": 35,
      "rsi_sell_threshold": 65,
      "rsi_to_buy": 17.26,
      "rsi_to_sell": 12.74,
      "price_above_ema200": true,
      "price_vs_ema200_pct": 0.92,
      "active_strategy": "RSI_EMA"
    },
    "ETHUSDT": {
      "price": 2352.08,
      "rsi": 45.07,
      "ema200": 2333.2372,
      "rsi_buy_threshold": 35,
      "rsi_sell_threshold": 65,
      "rsi_to_buy": 10.07,
      "rsi_to_sell": 19.93,
      "price_above_ema200": true,
      "price_vs_ema200_pct": 0.81,
      "active_strategy": "RSI_EMA"
    },
    "SOLUSDT": {
      "price": 85.18,
      "rsi": 52.85,
      "ema200": 84.4199,
      "rsi_buy_threshold": 35,
      "rsi_sell_threshold": 65,
      "rsi_to_buy": 17.85,
      "rsi_to_sell": 12.15,
      "price_above_ema200": true,
      "price_vs_ema200_pct": 0.9,
      "active_strategy": "RSI_EMA"
    }
  }
}