{
  "updated": "2026-04-19 23:08:55",
  "bot_config": {
    "active_strategy": "RSI_EMA",
    "rsi_buy": 35,
    "rsi_sell": 65,
    "stop_loss_pct": 2.0,
    "take_profit_pct": 4.0,
    "trade_usdt": 100.0,
    "candle_interval": "15m"
  },
  "balances": {
    "BTC": 0.99852,
    "USDT": 10287.639152,
    "ETH": 0.9505,
    "SOL": 3.838
  },
  "positions": {
    "BTCUSDT": {
      "dca_count": 0,
      "entries": []
    },
    "ETHUSDT": {
      "dca_count": 0,
      "entries": []
    },
    "SOLUSDT": {
      "dca_count": 0,
      "entries": []
    }
  },
  "indicators": {
    "BTCUSDT": {
      "price": 74084.38,
      "rsi": 28.25,
      "ema200": 75651.5019,
      "rsi_buy_threshold": 35,
      "rsi_sell_threshold": 65,
      "rsi_to_buy": -6.75,
      "rsi_to_sell": 36.75,
      "price_above_ema200": false,
      "price_vs_ema200_pct": -2.07,
      "active_strategy": "RSI_EMA"
    },
    "ETHUSDT": {
      "price": 2271.14,
      "rsi": 35.09,
      "ema200": 2339.189,
      "rsi_buy_threshold": 35,
      "rsi_sell_threshold": 65,
      "rsi_to_buy": 0.09,
      "rsi_to_sell": 29.91,
      "price_above_ema200": false,
      "price_vs_ema200_pct": -2.91,
      "active_strategy": "RSI_EMA"
    },
    "SOLUSDT": {
      "price": 83.84,
      "rsi": 29.83,
      "ema200": 86.3581,
      "rsi_buy_threshold": 35,
      "rsi_sell_threshold": 65,
      "rsi_to_buy": -5.17,
      "rsi_to_sell": 35.17,
      "price_above_ema200": false,
      "price_vs_ema200_pct": -2.92,
      "active_strategy": "RSI_EMA"
    }
  }
}