{
  "updated": "2026-05-05 13:40:34",
  "bot_config": {
    "active_strategy": "RSI_EMA",
    "rsi_buy": 35,
    "rsi_sell": 65,
    "stop_loss_pct": 2.0,
    "take_profit_pct": 4.0,
    "trade_usdt": 100.0,
    "candle_interval": "15m"
  },
  "balances": {
    "BTC": 0.99852,
    "USDT": 10277.1999156,
    "ETH": 0.9505,
    "SOL": 3.846
  },
  "positions": {
    "BTCUSDT": {
      "dca_count": 0,
      "entries": []
    },
    "ETHUSDT": {
      "dca_count": 0,
      "entries": []
    },
    "SOLUSDT": {
      "dca_count": 0,
      "entries": []
    }
  },
  "indicators": {
    "BTCUSDT": {
      "price": 81474.26,
      "rsi": 68.47,
      "ema200": 79966.9327,
      "rsi_buy_threshold": 35,
      "rsi_sell_threshold": 65,
      "rsi_to_buy": 33.47,
      "rsi_to_sell": -3.47,
      "price_above_ema200": true,
      "price_vs_ema200_pct": 1.88,
      "active_strategy": "RSI_EMA"
    },
    "ETHUSDT": {
      "price": 2389.89,
      "rsi": 61.04,
      "ema200": 2356.8872,
      "rsi_buy_threshold": 35,
      "rsi_sell_threshold": 65,
      "rsi_to_buy": 26.04,
      "rsi_to_sell": 3.96,
      "price_above_ema200": true,
      "price_vs_ema200_pct": 1.4,
      "active_strategy": "RSI_EMA"
    },
    "SOLUSDT": {
      "price": 85.69,
      "rsi": 70.87,
      "ema200": 84.5804,
      "rsi_buy_threshold": 35,
      "rsi_sell_threshold": 65,
      "rsi_to_buy": 35.87,
      "rsi_to_sell": -5.87,
      "price_above_ema200": true,
      "price_vs_ema200_pct": 1.31,
      "active_strategy": "RSI_EMA"
    }
  }
}