{
  "updated": "2026-04-25 10:11:31",
  "bot_config": {
    "active_strategy": "RSI_EMA",
    "rsi_buy": 35,
    "rsi_sell": 65,
    "stop_loss_pct": 2.0,
    "take_profit_pct": 4.0,
    "trade_usdt": 100.0,
    "candle_interval": "15m"
  },
  "balances": {
    "BTC": 0.99852,
    "USDT": 10276.4297388,
    "ETH": 0.9505,
    "SOL": 3.846
  },
  "positions": {
    "BTCUSDT": {
      "dca_count": 0,
      "entries": []
    },
    "ETHUSDT": {
      "dca_count": 0,
      "entries": []
    },
    "SOLUSDT": {
      "dca_count": 0,
      "entries": []
    }
  },
  "indicators": {
    "BTCUSDT": {
      "price": 77714.55,
      "rsi": 62.12,
      "ema200": 77831.5927,
      "rsi_buy_threshold": 35,
      "rsi_sell_threshold": 65,
      "rsi_to_buy": 27.12,
      "rsi_to_sell": 2.88,
      "price_above_ema200": false,
      "price_vs_ema200_pct": -0.15,
      "active_strategy": "RSI_EMA"
    },
    "ETHUSDT": {
      "price": 2319.01,
      "rsi": 53.89,
      "ema200": 2327.2529,
      "rsi_buy_threshold": 35,
      "rsi_sell_threshold": 65,
      "rsi_to_buy": 18.89,
      "rsi_to_sell": 11.11,
      "price_above_ema200": false,
      "price_vs_ema200_pct": -0.35,
      "active_strategy": "RSI_EMA"
    },
    "SOLUSDT": {
      "price": 86.58,
      "rsi": 56.75,
      "ema200": 86.2529,
      "rsi_buy_threshold": 35,
      "rsi_sell_threshold": 65,
      "rsi_to_buy": 21.75,
      "rsi_to_sell": 8.25,
      "price_above_ema200": true,
      "price_vs_ema200_pct": 0.38,
      "active_strategy": "RSI_EMA"
    }
  }
}