{
  "updated": "2026-04-01 22:27:38",
  "balances": {
    "BTC": 1.0,
    "USDT": 10106.22403,
    "ETH": 0.9505,
    "SOL": 5.0
  },
  "positions": {
    "BTCUSDT": {
      "dca_count": 1,
      "avg_entry_price": 66866.71,
      "take_profit_price": 69541.3784,
      "stop_loss_price": 65529.3758,
      "total_coin": 0.00149,
      "total_usdt": 99.63,
      "entries": [
        {
          "dca_level": 1,
          "entry_price": 66866.71,
          "coin_amount": 0.00149,
          "usdt_amount": 99.63
        }
      ]
    },
    "ETHUSDT": {
      "dca_count": 0,
      "entries": []
    },
    "SOLUSDT": {
      "dca_count": 1,
      "avg_entry_price": 82.83,
      "take_profit_price": 86.1432,
      "stop_loss_price": 81.1734,
      "total_coin": 1.207,
      "total_usdt": 99.98,
      "entries": [
        {
          "dca_level": 1,
          "entry_price": 82.83,
          "coin_amount": 1.207,
          "usdt_amount": 99.98
        }
      ]
    }
  },
  "indicators": {
    "BTCUSDT": {
      "price": 68209.6,
      "rsi": 50.67,
      "ema200": null,
      "rsi_buy_threshold": 35,
      "rsi_sell_threshold": 65,
      "rsi_to_buy": 15.67,
      "rsi_to_sell": 14.33,
      "price_above_ema200": null,
      "price_vs_ema200_pct": null,
      "active_strategy": "RSI_EMA"
    },
    "ETHUSDT": {
      "price": 2150.4,
      "rsi": 57.83,
      "ema200": null,
      "rsi_buy_threshold": 35,
      "rsi_sell_threshold": 65,
      "rsi_to_buy": 22.83,
      "rsi_to_sell": 7.17,
      "price_above_ema200": null,
      "price_vs_ema200_pct": null,
      "active_strategy": "RSI_EMA"
    },
    "SOLUSDT": {
      "price": 81.34,
      "rsi": 28.77,
      "ema200": null,
      "rsi_buy_threshold": 35,
      "rsi_sell_threshold": 65,
      "rsi_to_buy": -6.23,
      "rsi_to_sell": 36.23,
      "price_above_ema200": null,
      "price_vs_ema200_pct": null,
      "active_strategy": "RSI_EMA"
    }
  }
}