{
  "updated": "2026-04-27 23:56:14",
  "bot_config": {
    "active_strategy": "RSI_EMA",
    "rsi_buy": 35,
    "rsi_sell": 65,
    "stop_loss_pct": 2.0,
    "take_profit_pct": 4.0,
    "trade_usdt": 100.0,
    "candle_interval": "15m"
  },
  "balances": {
    "BTC": 0.99852,
    "USDT": 10273.9454528,
    "ETH": 0.9505,
    "SOL": 3.846
  },
  "positions": {
    "BTCUSDT": {
      "dca_count": 0,
      "entries": []
    },
    "ETHUSDT": {
      "dca_count": 0,
      "entries": []
    },
    "SOLUSDT": {
      "dca_count": 0,
      "entries": []
    }
  },
  "indicators": {
    "BTCUSDT": {
      "price": 77293.99,
      "rsi": 62.71,
      "ema200": 77672.0242,
      "rsi_buy_threshold": 35,
      "rsi_sell_threshold": 65,
      "rsi_to_buy": 27.71,
      "rsi_to_sell": 2.29,
      "price_above_ema200": false,
      "price_vs_ema200_pct": -0.49,
      "active_strategy": "RSI_EMA"
    },
    "ETHUSDT": {
      "price": 2299.13,
      "rsi": 58.63,
      "ema200": 2321.6832,
      "rsi_buy_threshold": 35,
      "rsi_sell_threshold": 65,
      "rsi_to_buy": 23.63,
      "rsi_to_sell": 6.37,
      "price_above_ema200": false,
      "price_vs_ema200_pct": -0.97,
      "active_strategy": "RSI_EMA"
    },
    "SOLUSDT": {
      "price": 84.75,
      "rsi": 59.54,
      "ema200": 85.7087,
      "rsi_buy_threshold": 35,
      "rsi_sell_threshold": 65,
      "rsi_to_buy": 24.54,
      "rsi_to_sell": 5.46,
      "price_above_ema200": false,
      "price_vs_ema200_pct": -1.12,
      "active_strategy": "RSI_EMA"
    }
  }
}