{
  "updated": "2026-04-17 11:24:16",
  "bot_config": {
    "active_strategy": "RSI_EMA",
    "rsi_buy": 35,
    "rsi_sell": 65,
    "stop_loss_pct": 2.0,
    "take_profit_pct": 4.0,
    "trade_usdt": 100.0,
    "candle_interval": "15m"
  },
  "balances": {
    "BTC": 0.99852,
    "USDT": 10305.4945992,
    "ETH": 0.9505,
    "SOL": 3.83
  },
  "positions": {
    "BTCUSDT": {
      "dca_count": 0,
      "entries": []
    },
    "ETHUSDT": {
      "dca_count": 0,
      "entries": []
    },
    "SOLUSDT": {
      "dca_count": 0,
      "entries": []
    }
  },
  "indicators": {
    "BTCUSDT": {
      "price": 75334.44,
      "rsi": 52.15,
      "ema200": 74736.4978,
      "rsi_buy_threshold": 35,
      "rsi_sell_threshold": 65,
      "rsi_to_buy": 17.15,
      "rsi_to_sell": 12.85,
      "price_above_ema200": true,
      "price_vs_ema200_pct": 0.8,
      "active_strategy": "RSI_EMA"
    },
    "ETHUSDT": {
      "price": 2347.58,
      "rsi": 53.35,
      "ema200": 2337.9557,
      "rsi_buy_threshold": 35,
      "rsi_sell_threshold": 65,
      "rsi_to_buy": 18.35,
      "rsi_to_sell": 11.65,
      "price_above_ema200": true,
      "price_vs_ema200_pct": 0.41,
      "active_strategy": "RSI_EMA"
    },
    "SOLUSDT": {
      "price": 87.81,
      "rsi": 44.05,
      "ema200": 86.548,
      "rsi_buy_threshold": 35,
      "rsi_sell_threshold": 65,
      "rsi_to_buy": 9.05,
      "rsi_to_sell": 20.95,
      "price_above_ema200": true,
      "price_vs_ema200_pct": 1.46,
      "active_strategy": "RSI_EMA"
    }
  }
}